statsmetrics/__init__.py
statsmetrics/couchbase.py
statsmetrics-1.0.2.dist-info/DESCRIPTION.rst
statsmetrics-1.0.2.dist-info/METADATA
statsmetrics-1.0.2.dist-info/RECORD
statsmetrics-1.0.2.dist-info/WHEEL
statsmetrics-1.0.2.dist-info/metadata.json
statsmetrics-1.0.2.dist-info/top_level.txt
