Metadata-Version: 2.0
Name: statsmetrics
Version: 1.0.2
Summary: List of metrics to use with exporters
Home-page: https://github.com/brunopsoares/statsmetrics
Author: Bruno Soares
Author-email: bruno.soares@jumia.com
License: MIT
Keywords: stats metrics analytics
Platform: UNKNOWN
Classifier: Development Status :: 5 - Production/Stable
Classifier: Environment :: Web Environment
Classifier: Intended Audience :: Developers
Classifier: License :: OSI Approved :: MIT License
Classifier: Programming Language :: Python :: 2
Classifier: Programming Language :: Python :: 2.7
Classifier: Programming Language :: Python :: 3
Classifier: Programming Language :: Python :: 3.5
